jsp_shaving1990/__init__.py
jsp_shaving1990/main.py
jsp_shaving1990/utils/__init__.py
jsp_shaving1990/utils/asc_set.py
jsp_shaving1990/utils/sort.py
jsp_shaving1990-0.1.51.dist-info/WHEEL
jsp_shaving1990-0.1.51.dist-info/METADATA
jsp_shaving1990-0.1.51.dist-info/RECORD
